fenix_bot_api/__init__.py
fenix_bot_api/comm.py
fenix_bot_api/command_create.py
fenix_bot_api/commands_system.py
fenix_bot_api/commands_user.py
fenix_bot_api/constants.py
fenix_bot_api/responses.py
fenix_bot_api/util.py
test/__init__.py
test/test_handle_response.py
fenix_bot_api-1.3.0.dist-info/LICENSE
fenix_bot_api-1.3.0.dist-info/METADATA
fenix_bot_api-1.3.0.dist-info/WHEEL
fenix_bot_api-1.3.0.dist-info/top_level.txt
fenix_bot_api-1.3.0.dist-info/RECORD
